tandamaster/__init__.py
tandamaster/__main__.py
tandamaster/app.py
tandamaster/commands.py
tandamaster/library.py
tandamaster/model.py
tandamaster/mp3splt.py
tandamaster/mp3splt_h.py
tandamaster/mutagen_easyaiff.py
tandamaster/mutagen_guess.py
tandamaster/player.py
tandamaster/replay_gain.py
tandamaster/tandamaster.py
tandamaster/ui.py
tandamaster/util.py
tandamaster/icons/Album-photo-icon.png
tandamaster/icons/button_fastforward_green.png
tandamaster/icons/button_pause_green.png
tandamaster/icons/button_play_green.png
tandamaster/icons/button_rewind_green.png
tandamaster/icons/button_stop_green.png
tandamaster/icons/circle_green.png
tandamaster/icons/crazyeye_dance.png
tandamaster/icons/happy-dance.gif
tandamaster/icons/image_album.png
tandamaster/icons/library.png
tandamaster/icons/personal.png
tandamaster/icons/song.png
tandamaster/icons/user.png
tandamaster/icons/user_awake.png
tandamaster/icons/iconarchive/icons8/Sports-Dancing-icon.png
tandamaster/icons/iconarchive/icons8/tandamaster-Sports-Dancing-icon.png
tandamaster/icons/iconfinder/32pxmania/arrow-down-right.png
tandamaster/icons/iconfinder/32pxmania/current_playtree.png
tandamaster/icons/iconfinder/32pxmania/delete.png
tandamaster/icons/iconfinder/32pxmania/down.png
tandamaster/icons/iconfinder/32pxmania/fast-forward.png
tandamaster/icons/iconfinder/32pxmania/insert.png
tandamaster/icons/iconfinder/32pxmania/left.png
tandamaster/icons/iconfinder/32pxmania/library.png
tandamaster/icons/iconfinder/32pxmania/next.png
tandamaster/icons/iconfinder/32pxmania/pause.png
tandamaster/icons/iconfinder/32pxmania/play.png
tandamaster/icons/iconfinder/32pxmania/previous.png
tandamaster/icons/iconfinder/32pxmania/redo.png
tandamaster/icons/iconfinder/32pxmania/rewind.png
tandamaster/icons/iconfinder/32pxmania/right.png
tandamaster/icons/iconfinder/32pxmania/undo.png
tandamaster/icons/iconfinder/32pxmania/up.png
tandamaster/icons/iconfinder/farm-fresh/copy.png
tandamaster/icons/iconfinder/farm-fresh/curtain.png
tandamaster-0.3.2.dist-info/licenses/LICENCE
tandamaster-0.3.2.dist-info/METADATA
tandamaster-0.3.2.dist-info/WHEEL
tandamaster-0.3.2.dist-info/entry_points.txt
tandamaster-0.3.2.dist-info/top_level.txt
tandamaster-0.3.2.dist-info/RECORD
