Metadata-Version: 2.4
Name: tandamaster
Version: 0.3.2
Summary: A music player specialized for playing music at milongas
Author-email: Sašo Živanović <saso.zivanovic@guest.arnes.si>
License-Expression: GPL-3.0-or-later
Project-URL: Repository, https://github.com/sasozivanovic/tandamaster
Keywords: tango
Classifier: Topic :: Multimedia :: Sound/Audio :: Players
Classifier: Development Status :: 4 - Beta
Classifier: Environment :: X11 Applications :: Qt
Classifier: Programming Language :: Python
Classifier: Intended Audience :: End Users/Desktop
License-File: LICENCE
Requires-Dist: PyQt5
Requires-Dist: PyGObject
Requires-Dist: mutagen
Requires-Dist: Unidecode
Requires-Dist: bidict
Requires-Dist: systemd-python
Requires-Dist: pydantic
Provides-Extra: debug
Requires-Dist: IPython; extra == "debug"
Dynamic: license-file
